dgtl_db_connector/__init__.py
dgtl_db_connector/client.py
dgtl_db_connector/customer.py
dgtl_db_connector/grader_pool.py
dgtl_db_connector/inventory.py
dgtl_db_connector/model.py
dgtl_db_connector/quality_control.py
dgtl_db_connector/role.py
dgtl_db_connector/user.py
DGTL_db_connector-0.1.8.dist-info/METADATA
DGTL_db_connector-0.1.8.dist-info/WHEEL
DGTL_db_connector-0.1.8.dist-info/top_level.txt
DGTL_db_connector-0.1.8.dist-info/RECORD
