Metadata-Version: 2.1
Name: DGTL_db_connector
Version: 0.1.8
Summary: AWS DynamoDB python wrapper with backward compatibility
Author: Olivier Witteman
License: MIT
Requires-Python: >=3.10
Requires-Dist: boto3
Requires-Dist: pandas
Requires-Dist: uuid
